{
  "products": [
    {
      "id": "1",
      "productName": "Pure",
      "price": 5000,
      "stock": 10,
      "active": false,
      "type": "Guarnicion"
    },
    {
      "id": "2",
      "productName": "Chorrillana",
      "price": 5600,
      "stock": 10,
      "type": "Guarnicion"
    }
  ],
  "users": [
    {
      "id": "3",
      "userName": "sebas",
      "fullName": "Sebastian Nunez",
      "email": "sa.nunezs@duocuc.cl",
      "password": "123456"
    },
    {
      "id": "1",
      "userName": "dpenaloza",
      "fullName": "Diego Peñaloza",
      "email": "die.penaloza@duocuc.cl",
      "password": "123456"
    }
  ]
}